icuraddmcpserver/__init__.py
icuraddmcpserver/server.py
icuraddmcpserver-0.1.0.dist-info/METADATA
icuraddmcpserver-0.1.0.dist-info/WHEEL
icuraddmcpserver-0.1.0.dist-info/entry_points.txt
icuraddmcpserver-0.1.0.dist-info/RECORD
