Metadata-Version: 2.4
Name: icuraddmcpserver
Version: 0.1.0
Summary: Add your description here
Author-email: ilaunchmoon <imoon_8295@163.com>
Requires-Python: >=3.12
Requires-Dist: mcp[cli]>=1.9.4
